langchain_mariadb/__init__.py
langchain_mariadb/_utils.py
langchain_mariadb/chat_message_histories.py
langchain_mariadb/expression_filter.py
langchain_mariadb/py.typed
langchain_mariadb/translator.py
langchain_mariadb/vectorstores.py
langchain_mariadb-0.0.20.dist-info/LICENSE
langchain_mariadb-0.0.20.dist-info/METADATA
langchain_mariadb-0.0.20.dist-info/WHEEL
langchain_mariadb-0.0.20.dist-info/RECORD
