Metadata-Version: 2.3
Name: langchain-mariadb
Version: 0.0.20
Summary: An integration package connecting MariaDB and LangChain
License: MIT
Requires-Python: >=3.10,<4.0
Classifier: License :: OSI Approved :: MIT License
Classifier: Programming Language :: Python :: 3
Classifier: Programming Language :: Python :: 3.10
Classifier: Programming Language :: Python :: 3.11
Classifier: Programming Language :: Python :: 3.12
Classifier: Programming Language :: Python :: 3.13
Requires-Dist: langchain-core (>=0.2.13,<2.0.0)
Requires-Dist: numpy (>=1.24,<3)
Requires-Dist: sqlalchemy (>=2,<3)
Project-URL: Source Code, https://github.com/mariadb-corporation/langchain-mariadb
